golden_dataset/__init__.py
golden_dataset/cli.py
golden_dataset/core.py
golden_dataset/exc.py
golden_dataset/main.py
golden_dataset-1.1.3.dist-info/METADATA
golden_dataset-1.1.3.dist-info/WHEEL
golden_dataset-1.1.3.dist-info/entry_points.txt
golden_dataset-1.1.3.dist-info/licenses/LICENSE
golden_dataset-1.1.3.dist-info/RECORD
