Metadata-Version: 2.4
Name: golden-dataset
Version: 1.1.3
Summary: Golden dataset management
Project-URL: Homepage, https://github.com/sethyates/golden-dataset
Project-URL: Bug Tracker, https://github.com/sethyates/golden-dataset/issues
Author-email: Seth Yates <29878+sethyates@users.noreply.github.com>
License-File: LICENSE
Classifier: License :: OSI Approved :: MIT License
Classifier: Operating System :: OS Independent
Classifier: Programming Language :: Python :: 3
Classifier: Programming Language :: Python :: 3.12
Requires-Python: >=3.12
Requires-Dist: importlib-metadata>=8.6.1
Requires-Dist: importlib-resources>=6.5.2
Requires-Dist: pydantic-settings[toml]>=2.8.1
Requires-Dist: pydantic>=2.10.6
Requires-Dist: sqlalchemy>=2.0.38
Provides-Extra: cli
Requires-Dist: rich>=13.9.4; extra == 'cli'
Requires-Dist: typer>=0.15.2; extra == 'cli'
Provides-Extra: dev
Requires-Dist: mypy>=1.14.1; extra == 'dev'
Requires-Dist: pytest-cov>=5.0.0; extra == 'dev'
Requires-Dist: pytest-sugar>=1.0.0; extra == 'dev'
Requires-Dist: pytest>=8.3.5; extra == 'dev'
Requires-Dist: rich>=13.9.4; extra == 'dev'
Requires-Dist: ruff>=0.9.9; extra == 'dev'
Requires-Dist: typer>=0.15.2; extra == 'dev'
